fileutils/__init__.py
fileutils/extension.py
fileutils/merge.py
fileutils/names.py
pdappendunits/__init__.py
pdappendunits/extension.py
pdappendunits/merge.py
pdappendunits/names.py
pdappendunits-0.2.dist-info/LICENSE
pdappendunits-0.2.dist-info/METADATA
pdappendunits-0.2.dist-info/WHEEL
pdappendunits-0.2.dist-info/top_level.txt
pdappendunits-0.2.dist-info/RECORD
