Metadata-Version: 2.1
Name: pdappendunits
Version: 0.2
Summary: A utility library for file operations
Home-page: https://github.com/Tanger-ine/mini_project/tree/main/pandas_appendunits
Author: Tanger-ine
Author-email: parak2065@gmail.com
License: MIT
License-File: LICENSE
Requires-Dist: pandas
